mlcube_ssh/__init__.py
mlcube_ssh/__main__.py
mlcube_ssh/ssh_metadata.py
mlcube_ssh/ssh_run.py
mlcube_ssh/tests/__init__.py
mlcube_ssh/tests/test_python_interpreters.py
mlcube_ssh/tests/test_data/platforms/platform_01.yaml
mlcube_ssh/tests/test_data/platforms/platform_02.yaml
mlcube_ssh-0.0.9.dist-info/METADATA
mlcube_ssh-0.0.9.dist-info/WHEEL
mlcube_ssh-0.0.9.dist-info/entry_points.txt
mlcube_ssh-0.0.9.dist-info/top_level.txt
mlcube_ssh-0.0.9.dist-info/RECORD
