Metadata-Version: 2.1
Name: mlcube-ssh
Version: 0.0.9
License: Apache 2.0
Requires-Python: >=3.6
Requires-Dist: mlcube (==0.0.9)
Requires-Dist: omegaconf (==2.1.0)
